pycounts_kari/__init__.py
pycounts_kari/plotting.py
pycounts_kari/pycounts_kari.py
pycounts_kari-0.1.2.dist-info/LICENSE
pycounts_kari-0.1.2.dist-info/WHEEL
pycounts_kari-0.1.2.dist-info/METADATA
pycounts_kari-0.1.2.dist-info/RECORD
