Metadata-Version: 2.1
Name: pycounts-kari
Version: 0.1.2
Summary: A tool for counting words.
License: MIT
Author: Katia A
Requires-Python: >=3.9,<4.0
Classifier: License :: OSI Approved :: MIT License
Classifier: Programming Language :: Python :: 3
Classifier: Programming Language :: Python :: 3.9
Requires-Dist: matplotlib (>=3.5.1,<4.0.0)
